sittagger/__init__.py
sittagger/__main__.py
sittagger/app.py
sittagger/birdeye.py
sittagger/canvas.py
sittagger/captiontools.py
sittagger/captionwidgets.py
sittagger/cli.py
sittagger/dbtag.py
sittagger/dirwidgets.py
sittagger/fileoperationdialog.py
sittagger/fm_interop.py
sittagger/fsops.py
sittagger/fullscreenviewer.py
sittagger/imagewidgets.py
sittagger/mainwindow.ui
sittagger/tagwidgets.py
sittagger/thumbnailmaker.py
sittagger/videogrid.py
sittagger/videowidgets.py
sittagger-1.1.2.data/data/share/applications/sittagger.desktop
sittagger-1.1.2.data/data/share/icons/hicolor/128x128/apps/sittagger.png
sittagger-1.1.2.dist-info/METADATA
sittagger-1.1.2.dist-info/WHEEL
sittagger-1.1.2.dist-info/entry_points.txt
sittagger-1.1.2.dist-info/licenses/COPYING.WTFPL
sittagger-1.1.2.dist-info/RECORD
