Metadata-Version: 2.4
Name: sittagger
Version: 1.1.2
Summary: Image viewer with user-labels tag database
Project-URL: Homepage, https://indigo.re/sit-tagger/
Project-URL: Project, https://gitlab.com/hydrargyrum/sit-tagger
Project-URL: PyPI, https://pypi.org/project/sittagger/
Author-email: Hg <dev@indigo.re>
License-Expression: WTFPL
License-File: COPYING.WTFPL
Keywords: browser,database,image,label,labelling,photo,python,tag,tagging,viewer
Classifier: Development Status :: 5 - Production/Stable
Classifier: Environment :: X11 Applications :: Qt
Classifier: Intended Audience :: End Users/Desktop
Classifier: License :: Public Domain
Classifier: Programming Language :: Python :: 3
Classifier: Programming Language :: Python :: 3 :: Only
Classifier: Programming Language :: Python :: 3.9
Classifier: Programming Language :: Python :: 3.10
Classifier: Programming Language :: Python :: 3.11
Classifier: Programming Language :: Python :: 3.12
Classifier: Programming Language :: Python :: 3.13
Classifier: Programming Language :: Python :: 3.14
Classifier: Topic :: Desktop Environment :: File Managers
Classifier: Topic :: Multimedia :: Graphics :: Viewers
Requires-Python: >=3.4
Requires-Dist: pyqt6
Requires-Dist: pyxdg
Requires-Dist: vignette
